LICENSE
MANIFEST.in
README.md
requirements.txt
setup.py
python_stackato.egg-info/PKG-INFO
python_stackato.egg-info/SOURCES.txt
python_stackato.egg-info/dependency_links.txt
python_stackato.egg-info/requires.txt
python_stackato.egg-info/top_level.txt
stackato/__init__.py
stackato/exceptions.py