Metadata-Version: 1.1
Name: python-stackato
Version: 1.4
Summary: Python interface to Stackato
Home-page: http://www.github.com/bacongobbler/python-stackato/
Author: Matthew Fisher
Author-email: me@bacongobbler.com
License: MIT License
Platform: UNKNOWN
Classifier: Development Status :: 3 - Alpha
Classifier: Intended Audience :: Developers
Classifier: Operating System :: OS Independent
Classifier: Programming Language :: Python
Classifier: Topic :: Software Development :: Libraries
Classifier: Topic :: Software Development :: Libraries :: Python Modules
